viskex/__init__.py
viskex/base_converter.py
viskex/base_plotter.py
viskex/dolfinx.py
viskex/dolfinx_converter.py
viskex/dolfinx_plotter.py
viskex/firedrake.py
viskex/firedrake_converter.py
viskex/firedrake_plotter.py
viskex/py.typed
viskex/pyvista_converter.py
viskex/pyvista_plotter.py
viskex/utils/__init__.py
viskex/utils/extract_part.py
viskex/utils/scalar_type.py
viskex/utils/values_in.py
viskex-0.1.0.post0.dist-info/licenses/AUTHORS
viskex-0.1.0.post0.dist-info/licenses/LICENSE
viskex-0.1.0.post0.dist-info/METADATA
viskex-0.1.0.post0.dist-info/WHEEL
viskex-0.1.0.post0.dist-info/top_level.txt
viskex-0.1.0.post0.dist-info/RECORD
